{
    "metadata": {
        "configurationVersions": [
            3
        ],
        "clusterVersion": "1.281.79.20231208-113952"
    },
    "id": "aaaaaaaa-bbbb-cccc-dddd-000000000173",
    "dashboardMetadata": {
        "name": "Oracle Extension 2",
        "shared": false,
        "owner": "nobody@example.com",
        "sharingDetails": {
            "linkShared": false,
            "published": false
        },
        "dashboardFilter": {
            "timeframe": "",
            "managementZone": null
        },
        "tags": [
            "Dynatrace Dashboard Generator"
        ],
        "preset": false,
        "tilesNameSize": "small",
        "hasConsistentColors": true
    },
    "tiles": [
        {
            "name": "Background CPU usage per core",
            "tileType": "DATA_EXPLORER",
            "configured": true,
            "bounds": {
                "top": 0,
                "left": 0,
                "width": 304,
                "height": 304
            },
            "tileFilter": {},
            "customName": "Background CPU usage per core",
            "queries": [
                {
                    "id": "A",
                    "metric": "func:com.dynatrace.extension.sql-oracle.cpu.background",
                    "spaceAggregation": "AVG",
                    "timeAggregation": "DEFAULT",
                    "splitBy": [
                        "dt.entity.sql:com_dynatrace_extension_sql-oracle_host"
                    ],
                    "filterBy": {
                        "filterOperator": "AND",
                        "nestedFilters": [],
                        "criteria": []
                    },
                    "enabled": true
                }
            ],
            "visualConfig": {
                "type": "GRAPH_CHART",
                "global": {
                    "theme": "DEFAULT",
                    "threshold": {
                        "axisTarget": "LEFT",
                        "rules": [
                            {
                                "color": "#7dc540"
                            },
                            {
                                "color": "#f5d30f"
                            },
                            {
                                "color": "#dc172a"
                            }
                        ]
                    },
                    "seriesType": "LINE"
                },
                "rules": [],
                "axes": {
                    "xAxis": {
                        "displayName": "",
                        "visible": true
                    },
                    "yAxes": [
                        {
                            "displayName": "",
                            "visible": true,
                            "min": "AUTO",
                            "max": "AUTO",
                            "position": "LEFT",
                            "queryIds": [
                                "A"
                            ],
                            "defaultAxis": true
                        }
                    ]
                }
            }
        },
        {
            "name": "Foreground CPU usage per core",
            "tileType": "DATA_EXPLORER",
            "configured": true,
            "bounds": {
                "top": 0,
                "left": 304,
                "width": 304,
                "height": 304
            },
            "tileFilter": {},
            "customName": "Foreground CPU usage per core",
            "queries": [
                {
                    "id": "A",
                    "metric": "func:com.dynatrace.extension.sql-oracle.cpu.foreground",
                    "spaceAggregation": "AVG",
                    "timeAggregation": "DEFAULT",
                    "splitBy": [],
                    "filterBy": {
                        "filterOperator": "AND",
                        "nestedFilters": [],
                        "criteria": []
                    },
                    "enabled": true
                }
            ],
            "visualConfig": {
                "type": "GRAPH_CHART",
                "global": {
                    "theme": "DEFAULT",
                    "threshold": {
                        "axisTarget": "LEFT",
                        "rules": [
                            {
                                "color": "#7dc540"
                            },
                            {
                                "color": "#f5d30f"
                            },
                            {
                                "color": "#dc172a"
                            }
                        ]
                    },
                    "seriesType": "LINE"
                },
                "rules": [],
                "axes": {
                    "xAxis": {
                        "displayName": "",
                        "visible": true
                    },
                    "yAxes": [
                        {
                            "displayName": "",
                            "visible": true,
                            "min": "AUTO",
                            "max": "AUTO",
                            "position": "LEFT",
                            "queryIds": [
                                "A"
                            ],
                            "defaultAxis": true
                        }
                    ]
                }
            }
        },
        {
            "name": "Host CPU usage per core",
            "tileType": "DATA_EXPLORER",
            "configured": true,
            "bounds": {
                "top": 0,
                "left": 608,
                "width": 304,
                "height": 304
            },
            "tileFilter": {},
            "customName": "Host CPU usage per core",
            "queries": [
                {
                    "id": "A",
                    "metric": "func:com.dynatrace.extension.sql-oracle.cpu.host",
                    "spaceAggregation": "AVG",
                    "timeAggregation": "DEFAULT",
                    "splitBy": [
                        "dt.entity.sql:com_dynatrace_extension_sql-oracle_host"
                    ],
                    "filterBy": {
                        "filterOperator": "AND",
                        "nestedFilters": [],
                        "criteria": []
                    },
                    "enabled": true
                }
            ],
            "visualConfig": {
                "type": "GRAPH_CHART",
                "global": {
                    "theme": "DEFAULT",
                    "threshold": {
                        "axisTarget": "LEFT",
                        "rules": [
                            {
                                "color": "#7dc540"
                            },
                            {
                                "color": "#f5d30f"
                            },
                            {
                                "color": "#dc172a"
                            }
                        ]
                    },
                    "seriesType": "LINE"
                },
                "rules": [],
                "axes": {
                    "xAxis": {
                        "displayName": "",
                        "visible": true
                    },
                    "yAxes": [
                        {
                            "displayName": "",
                            "visible": true,
                            "min": "AUTO",
                            "max": "AUTO",
                            "position": "LEFT",
                            "queryIds": [
                                "A"
                            ],
                            "defaultAxis": true
                        }
                    ]
                }
            }
        },
        {
            "name": "Foreground CPU usage per core",
            "tileType": "DATA_EXPLORER",
            "configured": true,
            "bounds": {
                "top": 0,
                "left": 912,
                "width": 304,
                "height": 304
            },
            "tileFilter": {},
            "customName": "Foreground CPU usage per core",
            "queries": [
                {
                    "id": "A",
                    "metric": "func:com.dynatrace.extension.sql-oracle.cpu.other",
                    "spaceAggregation": "AVG",
                    "timeAggregation": "DEFAULT",
                    "splitBy": [],
                    "filterBy": {
                        "filterOperator": "AND",
                        "nestedFilters": [],
                        "criteria": []
                    },
                    "enabled": true
                }
            ],
            "visualConfig": {
                "type": "GRAPH_CHART",
                "global": {
                    "theme": "DEFAULT",
                    "threshold": {
                        "axisTarget": "LEFT",
                        "rules": [
                            {
                                "color": "#7dc540"
                            },
                            {
                                "color": "#f5d30f"
                            },
                            {
                                "color": "#dc172a"
                            }
                        ]
                    },
                    "seriesType": "LINE"
                },
                "rules": [],
                "axes": {
                    "xAxis": {
                        "displayName": "",
                        "visible": true
                    },
                    "yAxes": [
                        {
                            "displayName": "",
                            "visible": true,
                            "min": "AUTO",
                            "max": "AUTO",
                            "position": "LEFT",
                            "queryIds": [
                                "A"
                            ],
                            "defaultAxis": true
                        }
                    ]
                }
            }
        },
        {
            "name": "Buffer cache hit ratio",
            "tileType": "DATA_EXPLORER",
            "configured": true,
            "bounds": {
                "top": 0,
                "left": 1216,
                "width": 304,
                "height": 304
            },
            "tileFilter": {},
            "customName": "Buffer cache hit ratio",
            "queries": [
                {
                    "id": "A",
                    "metric": "func:com.dynatrace.extension.sql-oracle.memory.bufferCacheHitRatio",
                    "spaceAggregation": "AVG",
                    "timeAggregation": "DEFAULT",
                    "splitBy": [
                        "dt.entity.sql:com_dynatrace_extension_sql-oracle_instance"
                    ],
                    "filterBy": {
                        "filterOperator": "AND",
                        "nestedFilters": [],
                        "criteria": []
                    },
                    "enabled": true
                }
            ],
            "visualConfig": {
                "type": "GRAPH_CHART",
                "global": {
                    "theme": "DEFAULT",
                    "threshold": {
                        "axisTarget": "LEFT",
                        "rules": [
                            {
                                "color": "#7dc540"
                            },
                            {
                                "color": "#f5d30f"
                            },
                            {
                                "color": "#dc172a"
                            }
                        ]
                    },
                    "seriesType": "LINE"
                },
                "rules": [],
                "axes": {
                    "xAxis": {
                        "displayName": "",
                        "visible": true
                    },
                    "yAxes": [
                        {
                            "displayName": "",
                            "visible": true,
                            "min": "AUTO",
                            "max": "AUTO",
                            "position": "LEFT",
                            "queryIds": [
                                "A"
                            ],
                            "defaultAxis": true
                        }
                    ]
                }
            }
        },
        {
            "name": "Target to limit ratio",
            "tileType": "DATA_EXPLORER",
            "configured": true,
            "bounds": {
                "top": 0,
                "left": 1520,
                "width": 304,
                "height": 304
            },
            "tileFilter": {},
            "customName": "Target to limit ratio",
            "queries": [
                {
                    "id": "A",
                    "metric": "func:com.dynatrace.extension.sql-oracle.memory.pga.size.targetToLimitRatio",
                    "spaceAggregation": "AVG",
                    "timeAggregation": "DEFAULT",
                    "splitBy": [
                        "dt.entity.sql:com_dynatrace_extension_sql-oracle_instance"
                    ],
                    "filterBy": {
                        "filterOperator": "AND",
                        "nestedFilters": [],
                        "criteria": []
                    },
                    "enabled": true
                }
            ],
            "visualConfig": {
                "type": "GRAPH_CHART",
                "global": {
                    "theme": "DEFAULT",
                    "threshold": {
                        "axisTarget": "LEFT",
                        "rules": [
                            {
                                "color": "#7dc540"
                            },
                            {
                                "color": "#f5d30f"
                            },
                            {
                                "color": "#dc172a"
                            }
                        ]
                    },
                    "seriesType": "LINE"
                },
                "rules": [],
                "axes": {
                    "xAxis": {
                        "displayName": "",
                        "visible": true
                    },
                    "yAxes": [
                        {
                            "displayName": "",
                            "visible": true,
                            "min": "AUTO",
                            "max": "AUTO",
                            "position": "LEFT",
                            "queryIds": [
                                "A"
                            ],
                            "defaultAxis": true
                        }
                    ]
                }
            }
        },
        {
            "name": "PGA used for work areas",
            "tileType": "DATA_EXPLORER",
            "configured": true,
            "bounds": {
                "top": 304,
                "left": 0,
                "width": 304,
                "height": 304
            },
            "tileFilter": {},
            "customName": "PGA used for work areas",
            "queries": [
                {
                    "id": "A",
                    "metric": "func:com.dynatrace.extension.sql-oracle.memory.pga.usedForWorkAreas",
                    "spaceAggregation": "AVG",
                    "timeAggregation": "DEFAULT",
                    "splitBy": [
                        "dt.entity.sql:com_dynatrace_extension_sql-oracle_instance"
                    ],
                    "filterBy": {
                        "filterOperator": "AND",
                        "nestedFilters": [],
                        "criteria": []
                    },
                    "enabled": true
                }
            ],
            "visualConfig": {
                "type": "GRAPH_CHART",
                "global": {
                    "theme": "DEFAULT",
                    "threshold": {
                        "axisTarget": "LEFT",
                        "rules": [
                            {
                                "color": "#7dc540"
                            },
                            {
                                "color": "#f5d30f"
                            },
                            {
                                "color": "#dc172a"
                            }
                        ]
                    },
                    "seriesType": "LINE"
                },
                "rules": [],
                "axes": {
                    "xAxis": {
                        "displayName": "",
                        "visible": true
                    },
                    "yAxes": [
                        {
                            "displayName": "",
                            "visible": true,
                            "min": "AUTO",
                            "max": "AUTO",
                            "position": "LEFT",
                            "queryIds": [
                                "A"
                            ],
                            "defaultAxis": true
                        }
                    ]
                }
            }
        },
        {
            "name": "Sorts in memory ratio",
            "tileType": "DATA_EXPLORER",
            "configured": true,
            "bounds": {
                "top": 304,
                "left": 304,
                "width": 304,
                "height": 304
            },
            "tileFilter": {},
            "customName": "Sorts in memory ratio",
            "queries": [
                {
                    "id": "A",
                    "metric": "func:com.dynatrace.extension.sql-oracle.memory.sortsInMemory",
                    "spaceAggregation": "AVG",
                    "timeAggregation": "DEFAULT",
                    "splitBy": [
                        "dt.entity.sql:com_dynatrace_extension_sql-oracle_instance"
                    ],
                    "filterBy": {
                        "filterOperator": "AND",
                        "nestedFilters": [],
                        "criteria": []
                    },
                    "enabled": true
                }
            ],
            "visualConfig": {
                "type": "GRAPH_CHART",
                "global": {
                    "theme": "DEFAULT",
                    "threshold": {
                        "axisTarget": "LEFT",
                        "rules": [
                            {
                                "color": "#7dc540"
                            },
                            {
                                "color": "#f5d30f"
                            },
                            {
                                "color": "#dc172a"
                            }
                        ]
                    },
                    "seriesType": "LINE"
                },
                "rules": [],
                "axes": {
                    "xAxis": {
                        "displayName": "",
                        "visible": true
                    },
                    "yAxes": [
                        {
                            "displayName": "",
                            "visible": true,
                            "min": "AUTO",
                            "max": "AUTO",
                            "position": "LEFT",
                            "queryIds": [
                                "A"
                            ],
                            "defaultAxis": true
                        }
                    ]
                }
            }
        },
        {
            "name": "Time spent on other activities",
            "tileType": "DATA_EXPLORER",
            "configured": true,
            "bounds": {
                "top": 304,
                "left": 608,
                "width": 304,
                "height": 304
            },
            "tileFilter": {},
            "customName": "Time spent on other activities",
            "queries": [
                {
                    "id": "A",
                    "metric": "func:com.dynatrace.extension.sql-oracle.queries.other",
                    "spaceAggregation": "AVG",
                    "timeAggregation": "DEFAULT",
                    "splitBy": [
                        "dt.entity.sql:com_dynatrace_extension_sql-oracle_instance"
                    ],
                    "filterBy": {
                        "filterOperator": "AND",
                        "nestedFilters": [],
                        "criteria": []
                    },
                    "enabled": true
                }
            ],
            "visualConfig": {
                "type": "GRAPH_CHART",
                "global": {
                    "theme": "DEFAULT",
                    "threshold": {
                        "axisTarget": "LEFT",
                        "rules": [
                            {
                                "color": "#7dc540"
                            },
                            {
                                "color": "#f5d30f"
                            },
                            {
                                "color": "#dc172a"
                            }
                        ]
                    },
                    "seriesType": "LINE"
                },
                "rules": [],
                "axes": {
                    "xAxis": {
                        "displayName": "",
                        "visible": true
                    },
                    "yAxes": [
                        {
                            "displayName": "",
                            "visible": true,
                            "min": "AUTO",
                            "max": "AUTO",
                            "position": "LEFT",
                            "queryIds": [
                                "A"
                            ],
                            "defaultAxis": true
                        }
                    ]
                }
            }
        },
        {
            "name": "Sessions to limit ratio",
            "tileType": "DATA_EXPLORER",
            "configured": true,
            "bounds": {
                "top": 304,
                "left": 912,
                "width": 304,
                "height": 304
            },
            "tileFilter": {},
            "customName": "Sessions to limit ratio",
            "queries": [
                {
                    "id": "A",
                    "metric": "func:com.dynatrace.extension.sql-oracle.sessions.totalSessionsToLimitRatio",
                    "spaceAggregation": "AVG",
                    "timeAggregation": "DEFAULT",
                    "splitBy": [
                        "dt.entity.sql:com_dynatrace_extension_sql-oracle_instance"
                    ],
                    "filterBy": {
                        "filterOperator": "AND",
                        "nestedFilters": [],
                        "criteria": []
                    },
                    "enabled": true
                }
            ],
            "visualConfig": {
                "type": "GRAPH_CHART",
                "global": {
                    "theme": "DEFAULT",
                    "threshold": {
                        "axisTarget": "LEFT",
                        "rules": [
                            {
                                "color": "#7dc540"
                            },
                            {
                                "color": "#f5d30f"
                            },
                            {
                                "color": "#dc172a"
                            }
                        ]
                    },
                    "seriesType": "LINE"
                },
                "rules": [],
                "axes": {
                    "xAxis": {
                        "displayName": "",
                        "visible": true
                    },
                    "yAxes": [
                        {
                            "displayName": "",
                            "visible": true,
                            "min": "AUTO",
                            "max": "AUTO",
                            "position": "LEFT",
                            "queryIds": [
                                "A"
                            ],
                            "defaultAxis": true
                        }
                    ]
                }
            }
        },
        {
            "name": "Used space ratio",
            "tileType": "DATA_EXPLORER",
            "configured": true,
            "bounds": {
                "top": 304,
                "left": 1216,
                "width": 304,
                "height": 304
            },
            "tileFilter": {},
            "customName": "Used space ratio",
            "queries": [
                {
                    "id": "A",
                    "metric": "func:com.dynatrace.extension.sql-oracle.tablespaces.usedRatio",
                    "spaceAggregation": "AVG",
                    "timeAggregation": "DEFAULT",
                    "splitBy": [
                        "dt.entity.sql:com_dynatrace_extension_sql-oracle_instance"
                    ],
                    "filterBy": {
                        "filterOperator": "AND",
                        "nestedFilters": [],
                        "criteria": []
                    },
                    "enabled": true
                }
            ],
            "visualConfig": {
                "type": "GRAPH_CHART",
                "global": {
                    "theme": "DEFAULT",
                    "threshold": {
                        "axisTarget": "LEFT",
                        "rules": [
                            {
                                "color": "#7dc540"
                            },
                            {
                                "color": "#f5d30f"
                            },
                            {
                                "color": "#dc172a"
                            }
                        ]
                    },
                    "seriesType": "LINE"
                },
                "rules": [],
                "axes": {
                    "xAxis": {
                        "displayName": "",
                        "visible": true
                    },
                    "yAxes": [
                        {
                            "displayName": "",
                            "visible": true,
                            "min": "AUTO",
                            "max": "AUTO",
                            "position": "LEFT",
                            "queryIds": [
                                "A"
                            ],
                            "defaultAxis": true
                        }
                    ]
                }
            }
        },
        {
            "name": "Used space",
            "tileType": "DATA_EXPLORER",
            "configured": true,
            "bounds": {
                "top": 304,
                "left": 1520,
                "width": 304,
                "height": 304
            },
            "tileFilter": {},
            "customName": "Used space",
            "queries": [
                {
                    "id": "A",
                    "metric": "func:com.dynatrace.extension.sql-oracle.tablespaces.usedSpace",
                    "spaceAggregation": "AVG",
                    "timeAggregation": "DEFAULT",
                    "splitBy": [
                        "dt.entity.sql:com_dynatrace_extension_sql-oracle_instance"
                    ],
                    "filterBy": {
                        "filterOperator": "AND",
                        "nestedFilters": [],
                        "criteria": []
                    },
                    "enabled": true
                }
            ],
            "visualConfig": {
                "type": "GRAPH_CHART",
                "global": {
                    "theme": "DEFAULT",
                    "threshold": {
                        "axisTarget": "LEFT",
                        "rules": [
                            {
                                "color": "#7dc540"
                            },
                            {
                                "color": "#f5d30f"
                            },
                            {
                                "color": "#dc172a"
                            }
                        ]
                    },
                    "seriesType": "LINE"
                },
                "rules": [],
                "axes": {
                    "xAxis": {
                        "displayName": "",
                        "visible": true
                    },
                    "yAxes": [
                        {
                            "displayName": "",
                            "visible": true,
                            "min": "AUTO",
                            "max": "AUTO",
                            "position": "LEFT",
                            "queryIds": [
                                "A"
                            ],
                            "defaultAxis": true
                        }
                    ]
                }
            }
        }
    ]
}