{
    "metadata": {
        "configurationVersions": [
            6
        ],
        "clusterVersion": "1.261.134.20230302-084304"
    },
    "id": "00000000-dddd-bbbb-ffff-000000000900",
    "dashboardMetadata": {
        "name": "TEMPLATE: Detailed Drilldowns Menu",
        "shared": true,
        "owner": "nobody@example.com",
        "hasConsistentColors": true,
        "tilesNameSize": "small"
    },
    "tiles": [
        {
            "name": "Markdown",
            "tileType": "MARKDOWN",
            "configured": true,
            "bounds": {
                "top": 0,
                "left": 0,
                "width": 608,
                "height": 532
            },
            "tileFilter": {},
            "isAutoRefreshDisabled": false,
            "markdown": "___\n## \ud83d\udd0d  Applications\n___  \n[Frontend/Applications](#uemapplications)  \n[Web Applications](#uemapplications;appsshown=webapps)  \n[Mobile Applications](#uemapplications;appsshown=mobileapps)  \n[Custom Applications](#uemapplications;appsshown=customapps)  \n[Session Segmentation](/ui/user-sessions)  \n[Query User Sessions](/ui/user-sessions/query)  \n[Session Replay](/ui/user-sessions/replay-landing)"
        },
        {
            "name": "Markdown",
            "tileType": "MARKDOWN",
            "configured": true,
            "bounds": {
                "top": 0,
                "left": 608,
                "width": 608,
                "height": 532
            },
            "tileFilter": {},
            "isAutoRefreshDisabled": false,
            "markdown": "___\n## \ud83d\udd0d  Services\n___  \n[Services](/ui/services)  \n[Distributed Traces/PurePaths](/ui/diagnostictools/purepaths)  \n[Multidimensional Analysis](/ui/diagnostictools)  \n[Top Web Requests](/ui/diagnostictools/mda?mdaId=topweb)  \n[Top Database Statements](/ui/diagnostictools/mda?mdaId=topdb)  \n[Exception Analysis](/ui/diagnostictools/mda?mdaId=exceptions)  \n [HTTP 4xx Details](/ui/diagnostictools/mda?metric=REQUEST_COUNT&dimension=%7BHTTP-Status%7D%20%7BHTTP-Method%7D%20%7BRequest:Name%7D&mergeServices=true&aggregation=COUNT&percentile=80&chart=COLUMN&servicefilter=0%1E26%112%1026%111%102%11400-499)  \n [HTTP 4xx Summary](/ui/diagnostictools/mda?metric=REQUEST_COUNT&dimension=%7BHTTP-Status%7D&mergeServices=true&aggregation=COUNT&percentile=80&chart=COLUMN&servicefilter=0%1E26%112%1026%111%102%11400-499)  \n [HTTP 5xx Details](/ui/diagnostictools/mda?metric=REQUEST_COUNT&dimension=%7BHTTP-Status%7D%20%7BHTTP-Method%7D%20%7BRequest:Name%7D&mergeServices=true&aggregation=COUNT&percentile=80&chart=COLUMN&servicefilter=0%1E26%112%1026%111%102%11500-599)  \n [HTTP 5xx Summary](/ui/diagnostictools/mda?metric=REQUEST_COUNT&dimension=%7BHTTP-Status%7D&mergeServices=true&aggregation=COUNT&percentile=80&chart=COLUMN&servicefilter=0%1E26%112%1026%111%102%11500-599)  \n [HTTP 5xx by Exception](/ui/diagnostictools/mda?metric=HTTP_5XX_ERROR_COUNT&dimension=%7BException:Class%7D&mergeServices=true&aggregation=COUNT&percentile=80&chart=COLUMN&servicefilter=0%1E29%110%140)  \n [HTTP No Response Details](/ui/diagnostictools/mda?metric=REQUEST_COUNT&dimension=%7BHTTP-Status%7D%20%7BHTTP-Method%7D%20%7BRequest:Name%7D&mergeServices=true&aggregation=COUNT&percentile=80&chart=COLUMN&servicefilter=0%1E26%112%1026%111%102%11-1)  \n [Long Lock Times](/ui/diagnostictools/mda?metric=LOCK_TIME&dimension=%7BRequest:Name%7D&mergeServices=false&aggregation=P90&percentile=80&chart=COLUMN&servicefilter=0%1E20%111%144611686018427387)  \n [Long Wait Times](/ui/diagnostictools/mda?metric=WAIT_TIME&dimension=%7BRequest:Name%7D&mergeServices=false&aggregation=P90&percentile=80&chart=LINE&servicefilter=0%1E26%112%1026%111%1019%111000%144611686018427387)  \n [Slow Web Requests](/ui/diagnostictools/mda?metric=RESPONSE_TIME&dimension=%7BRequest:Name%7D&mergeServices=false&aggregation=AVERAGE&percentile=80&chart=COLUMN&servicefilter=0%1E26%112%1026%111%100%116000000%144611686018427387)  \n [Slow Web Requests: Percentile](/ui/diagnostictools/mda?metric=RESPONSE_TIME&dimension=%7BRequest:Name%7D%20&mergeServices=false&aggregation=P90&percentile=80&chart=COLUMN&servicefilter=0%1E26%111%1026%112%100%116000000%144611686018427387)  \n[Key Requests: Failures](/ui/diagnostictools/mda?metric=FAILED_REQUEST_COUNT&dimension=%7BRequest:Name%7D&mergeServices=false&aggregation=COUNT&percentile=80&chart=COLUMN&servicefilter=0%1E61%110)  \n[Key Requests: Slowness](/ui/diagnostictools/mda?metric=RESPONSE_TIME&dimension=%7BRequest:Name%7D&mergeServices=false&aggregation=P90&percentile=80&chart=COLUMN&servicefilter=0%1E61%110%100%116000000%144611686018427387)  \n"
        },
        {
            "name": "Markdown",
            "tileType": "MARKDOWN",
            "configured": true,
            "bounds": {
                "top": 0,
                "left": 1216,
                "width": 608,
                "height": 266
            },
            "tileFilter": {},
            "isAutoRefreshDisabled": false,
            "markdown": "___\n## \ud83d\udd0d  Processes\n___  \n[Processes](#newprocessessummary)  \n[CPU Profiling](/ui/profiling-optimization)  \n[Process Crashes](#processcrashesglobal)  \n[Memory Dumps](/ui/diagnostictools/memorydumps)"
        },
        {
            "name": "Markdown",
            "tileType": "MARKDOWN",
            "configured": true,
            "bounds": {
                "top": 0,
                "left": 1824,
                "width": 152,
                "height": 38
            },
            "tileFilter": {},
            "markdown": "#### [\u21e6 Overview](#dashboard;id=00000000-dddd-bbbb-ffff-000000000001)\n![BackButton]()"
        },
        {
            "name": "Markdown",
            "tileType": "MARKDOWN",
            "configured": true,
            "bounds": {
                "top": 266,
                "left": 1216,
                "width": 608,
                "height": 266
            },
            "tileFilter": {},
            "isAutoRefreshDisabled": false,
            "markdown": "___\n## \ud83d\udd0d  Hosts\n___  \n[Hosts](#newhosts)  \n[Network](/ui/network)"
        },
        {
            "name": "Markdown",
            "tileType": "MARKDOWN",
            "configured": true,
            "bounds": {
                "top": 532,
                "left": 0,
                "width": 608,
                "height": 266
            },
            "tileFilter": {},
            "isAutoRefreshDisabled": false,
            "markdown": "___\n## \ud83d\udd0d  Synthetics\n___  \n[Synthetic](#monitors)"
        },
        {
            "name": "Markdown",
            "tileType": "MARKDOWN",
            "configured": true,
            "bounds": {
                "top": 532,
                "left": 608,
                "width": 608,
                "height": 266
            },
            "tileFilter": {},
            "isAutoRefreshDisabled": false,
            "markdown": "___\n## \ud83d\udd0d  Databases\n___  \n[Databases](/ui/databases)  \n[Failed Queries](/ui/diagnostictools/mda?metric=FAILED_REQUEST_COUNT&dimension=%7BRequest:Name%7D&mergeServices=false&aggregation=COUNT&percentile=80&chart=COLUMN&servicefilter=0%1E26%110%103%110)  \n[Number of DB Calls](/ui/diagnostictools/mda?metric=DATABASE_CHILD_CALL_COUNT&dimension=%7BRequest:Name%7D&mergeServices=false&aggregation=AVERAGE&percentile=80&chart=COLUMN&servicefilter=0%1E37%111%144611686018427387)  \n[Slow Queries](/ui/diagnostictools/mda?metric=RESPONSE_TIME&dimension=%7BRequest:Name%7D&mergeServices=false&aggregation=AVERAGE&percentile=80&chart=COLUMN&servicefilter=0%1E26%110%100%111000000%144611686018427387)"
        },
        {
            "name": "Markdown",
            "tileType": "MARKDOWN",
            "configured": true,
            "bounds": {
                "top": 532,
                "left": 1216,
                "width": 608,
                "height": 266
            },
            "tileFilter": {},
            "isAutoRefreshDisabled": false,
            "markdown": "___\n## \ud83d\udd0d  Others\n___  \n[Smartscape](#smartscape)  \n[Azure](#azures)  \n[VMware](#vcenters)  \n[Kubernetes](/ui/entity/list/KUBERNETES_CLUSTER)  \n[Kubernetes Workloads](/ui/entity/list/CLOUD_APPLICATION)  \n[Containers](/ui/entity/list/CONTAINER_GROUP)  \n[Docker](#docker)  \n[Extensions/Hub](/ui/hub?#extensions)  \n[Custom Devices](#newcustomdevices)"
        }
    ]
}