{
  "metadata": {
    "configurationVersions": [
      7
    ],
    "clusterVersion": "1.333.57.20260305-233338"
  },
  "id": "d926f9eb-9b93-4b36-947c-26f4f82f30c3",
  "dashboardMetadata": {
    "name": "Executive-Prototype",
    "shared": true,
    "owner": "dave.mauney@dynatrace.com",
    "preset": true,
    "popularity": 2,
    "tilesNameSize": "small",
    "hasConsistentColors": true
  },
  "tiles": [
    {
      "name": "All Problems",
      "nameSize": "large",
      "tileType": "OPEN_PROBLEMS",
      "configured": true,
      "bounds": {
        "top": 0,
        "left": 0,
        "width": 570,
        "height": 152
      },
      "tileFilter": {},
      "isAutoRefreshDisabled": false
    },
    {
      "name": "Tier 1 Problems",
      "nameSize": "large",
      "tileType": "OPEN_PROBLEMS",
      "configured": true,
      "bounds": {
        "top": 152,
        "left": 0,
        "width": 570,
        "height": 152
      },
      "tileFilter": {
        "managementZone": {
          "id": "958600393478977168",
          "name": "TIER:1"
        }
      },
      "isAutoRefreshDisabled": false
    },
    {
      "name": "Non Tier 1 Problems",
      "nameSize": "large",
      "tileType": "OPEN_PROBLEMS",
      "configured": true,
      "bounds": {
        "top": 304,
        "left": 0,
        "width": 570,
        "height": 152
      },
      "tileFilter": {
        "managementZone": {
          "id": "-1959809660664269378",
          "name": "TIER:0"
        }
      },
      "isAutoRefreshDisabled": false
    },
    {
      "name": "accounting Problems",
      "nameSize": "large",
      "tileType": "OPEN_PROBLEMS",
      "configured": true,
      "bounds": {
        "top": 456,
        "left": 0,
        "width": 570,
        "height": 152
      },
      "tileFilter": {
        "managementZone": {
          "id": "1839927316879455757",
          "name": "APP:accounting"
        }
      },
      "isAutoRefreshDisabled": false
    }
  ]
}