{
    "metadata": {
        "configurationVersions": [
            6
        ],
        "clusterVersion": "1.253.206.20221104-095518"
    },
    "id": "aaaaaaaa-bbbb-cccc-eeee-f00000000034",
    "dashboardMetadata": {
        "name": "AWS Billing",
        "shared": false,
        "owner": "nobody@example.com",
        "dashboardFilter": null,
        "tags": [
            "Aws Monitoring"
        ],
        "preset": true,
        "popularity": 1,
        "tilesNameSize": null,
        "hasConsistentColors": false
    },
    "tiles": [
        {
            "name": "Estimated charges",
            "nameSize": null,
            "tileType": "HEADER",
            "configured": true,
            "bounds": {
                "top": 0,
                "left": 0,
                "width": 418,
                "height": 38
            },
            "tileFilter": {
                "timeframe": null,
                "managementZone": null
            }
        },
        {
            "name": "Estimated charges per service",
            "tileType": "DATA_EXPLORER",
            "configured": true,
            "bounds": {
                "top": 304,
                "left": 0,
                "width": 418,
                "height": 494
            },
            "tileFilter": {},
            "customName": "Estimated charges per service",
            "queries": [
                {
                    "id": "A",
                    "metric": "ext:cloud.aws.billing.estimatedChargesByCurrency",
                    "spaceAggregation": "MAX",
                    "timeAggregation": "DEFAULT",
                    "splitBy": [
                        "dt.entity.custom_device",
                        "Currency"
                    ],
                    "filterBy": {
                        "filterOperator": "AND",
                        "nestedFilters": [],
                        "criteria": []
                    },
                    "enabled": true
                }
            ],
            "visualConfig": {
                "type": "TOP_LIST",
                "global": {
                    "theme": "DEFAULT",
                    "threshold": {
                        "axisTarget": "LEFT",
                        "rules": [
                            {
                                "color": "#7dc540"
                            },
                            {
                                "color": "#f5d30f"
                            },
                            {
                                "color": "#dc172a"
                            }
                        ],
                        "visible": true
                    },
                    "seriesType": "LINE",
                    "hideLegend": false
                },
                "rules": [],
                "axes": {
                    "xAxis": {
                        "displayName": "",
                        "visible": true
                    },
                    "yAxes": [
                        {
                            "displayName": "",
                            "visible": true,
                            "min": "AUTO",
                            "max": "AUTO",
                            "position": "LEFT",
                            "queryIds": [
                                "A"
                            ],
                            "defaultAxis": true
                        }
                    ]
                },
                "thresholds": [
                    {
                        "axisTarget": "LEFT",
                        "rules": [
                            {
                                "color": "#7dc540"
                            },
                            {
                                "color": "#f5d30f"
                            },
                            {
                                "color": "#dc172a"
                            }
                        ],
                        "visible": true
                    }
                ]
            }
        },
        {
            "name": "Estimated charges for all services",
            "tileType": "DATA_EXPLORER",
            "configured": true,
            "bounds": {
                "top": 38,
                "left": 0,
                "width": 418,
                "height": 266
            },
            "tileFilter": {},
            "customName": "Estimated charges for all services",
            "queries": [
                {
                    "id": "A",
                    "metric": "ext:cloud.aws.billing.estimatedChargesByRegionCurrency",
                    "spaceAggregation": "MAX",
                    "timeAggregation": "DEFAULT",
                    "splitBy": [
                        "Currency"
                    ],
                    "filterBy": {
                        "filterOperator": "AND",
                        "nestedFilters": [],
                        "criteria": []
                    },
                    "enabled": true
                }
            ],
            "visualConfig": {
                "type": "SINGLE_VALUE",
                "global": {
                    "theme": "DEFAULT",
                    "threshold": {
                        "axisTarget": "LEFT",
                        "rules": [
                            {
                                "color": "#7dc540"
                            },
                            {
                                "color": "#f5d30f"
                            },
                            {
                                "color": "#dc172a"
                            }
                        ],
                        "visible": true
                    },
                    "seriesType": "LINE",
                    "hideLegend": false
                },
                "rules": [],
                "axes": {
                    "xAxis": {
                        "displayName": "",
                        "visible": true
                    },
                    "yAxes": [
                        {
                            "displayName": "",
                            "visible": true,
                            "min": "AUTO",
                            "max": "AUTO",
                            "position": "LEFT",
                            "queryIds": [
                                "A"
                            ],
                            "defaultAxis": true
                        }
                    ]
                },
                "thresholds": [
                    {
                        "axisTarget": "LEFT",
                        "rules": [
                            {
                                "color": "#7dc540"
                            },
                            {
                                "color": "#f5d30f"
                            },
                            {
                                "color": "#dc172a"
                            }
                        ],
                        "visible": true
                    }
                ]
            }
        }
    ]
}